{
   "agent": "ws@8.17.0",
   "behavior": "OK",
   "behaviorClose": "OK",
   "case": 22,
   "closedByMe": true,
   "createStats": true,
   "createWirelog": true,
   "description": "Send ping with binary payload of 125 octets, send in octet-wise chops.",
   "droppedByMe": true,
   "duration": 30,
   "expectation": "Pong with payload echo'ed is sent in reply to Ping. Implementations must be TCP clean. Clean close with normal code.",
   "expected": {
      "OK": [
         [
            "pong",
            "0xfefefefefefefefefefefefefefefefefefefefefefefefefefefefefefefefefefefefefefefefefefefefefefefefefefefefefefefefefefefefefefefefe ..."
         ]
      ]
   },
   "expectedClose": {
      "closeCode": [
         1000
      ],
      "closedByMe": true,
      "requireClean": true
   },
   "failedByMe": false,
   "httpRequest": "GET /runCase?case=22&agent=ws@8.17.0 HTTP/1.1\r\nSec-WebSocket-Version: 13\r\nSec-WebSocket-Key: nTUZLmRYMQZdhaIQ9Rtdsw==\r\nConnection: Upgrade\r\nUpgrade: websocket\r\nSec-WebSocket-Extensions: permessage-deflate; client_max_window_bits\r\nHost: localhost:9001\r\n\r\n",
   "httpResponse": "HTTP/1.1 101 Switching Protocols\r\nServer: AutobahnTestSuite/0.8.2-0.10.9\r\nX-Powered-By: AutobahnPython/0.10.9\r\nUpgrade: WebSocket\r\nConnection: Upgrade\r\nSec-WebSocket-Accept: +DKTn7tpAT+/4PPx7VR0ViGng54=\r\n\r\n",
   "id": "2.6",
   "isServer": true,
   "localCloseCode": 1000,
   "localCloseReason": null,
   "received": [
      [
         "pong",
         "0xfefefefefefefefefefefefefefefefefefefefefefefefefefefefefefefefefefefefefefefefefefefefefefefefefefefefefefefefefefefefefefefefe ..."
      ]
   ],
   "remoteCloseCode": 1000,
   "remoteCloseReason": null,
   "reportCompressionRatio": false,
   "reportTime": false,
   "result": "Actual events match at least one expected.",
   "resultClose": "Connection was properly closed",
   "rxFrameStats": {
      "8": 1,
      "10": 1
   },
   "rxOctetStats": {
      "8": 1,
      "131": 1,
      "254": 1
   },
   "started": "2024-05-17T17:42:49.036Z",
   "trafficStats": null,
   "txFrameStats": {
      "8": 1,
      "9": 1
   },
   "txOctetStats": {
      "1": 127,
      "4": 1,
      "206": 1
   },
   "wasClean": true,
   "wasCloseHandshakeTimeout": false,
   "wasNotCleanReason": null,
   "wasOpenHandshakeTimeout": false,
   "wasServerConnectionDropTimeout": false,
   "wirelog": [
      [
         "RO",
         [
            254,
            "474554202f72756e436173653f636173653d3232266167656e743d777340382e31372e3020485454502f312e310d0a5365632d576562536f636b65742d566572 ..."
         ]
      ],
      [
         "TO",
         [
            206,
            "485454502f312e312031303120537769746368696e672050726f746f636f6c730d0a5365727665723a204175746f6261686e5465737453756974652f302e382e ..."
         ],
         false
      ],
      [
         "TF",
         [
            125,
            "0xfefefefefefefefefefefefefefefefefefefefefefefefefefefefefefefefefefefefefefefefefefefefefefefefefefefefefefefefefefefefefefefefe ..."
         ],
         9,
         true,
         0,
         null,
         null,
         1,
         false
      ],
      [
         "TO",
         [
            1,
            "89"
         ],
         true
      ],
      [
         "TI",
         2
      ],
      [
         "TO",
         [
            1,
            "7d"
         ],
         true
      ],
      [
         "TO",
         [
            1,
            "fe"
         ],
         true
      ],
      [
         "TO",
         [
            1,
            "fe"
         ],
         true
      ],
      [
         "TO",
         [
            1,
            "fe"
         ],
         true
      ],
      [
         "TO",
         [
            1,
            "fe"
         ],
         true
      ],
      [
         "TO",
         [
            1,
            "fe"
         ],
         true
      ],
      [
         "TO",
         [
            1,
            "fe"
         ],
         true
      ],
      [
         "TO",
         [
            1,
            "fe"
         ],
         true
      ],
      [
         "TO",
         [
            1,
            "fe"
         ],
         true
      ],
      [
         "TO",
         [
            1,
            "fe"
         ],
         true
      ],
      [
         "TO",
         [
            1,
            "fe"
         ],
         true
      ],
      [
         "TO",
         [
            1,
            "fe"
         ],
         true
      ],
      [
         "TO",
         [
            1,
            "fe"
         ],
         true
      ],
      [
         "TO",
         [
            1,
            "fe"
         ],
         true
      ],
      [
         "TO",
         [
            1,
            "fe"
         ],
         true
      ],
      [
         "TO",
         [
            1,
            "fe"
         ],
         true
      ],
      [
         "TO",
         [
            1,
            "fe"
         ],
         true
      ],
      [
         "TO",
         [
            1,
            "fe"
         ],
         true
      ],
      [
         "TO",
         [
            1,
            "fe"
         ],
         true
      ],
      [
         "TO",
         [
            1,
            "fe"
         ],
         true
      ],
      [
         "TO",
         [
            1,
            "fe"
         ],
         true
      ],
      [
         "TO",
         [
            1,
            "fe"
         ],
         true
      ],
      [
         "TO",
         [
            1,
            "fe"
         ],
         true
      ],
      [
         "TO",
         [
            1,
            "fe"
         ],
         true
      ],
      [
         "TO",
         [
            1,
            "fe"
         ],
         true
      ],
      [
         "TO",
         [
            1,
            "fe"
         ],
         true
      ],
      [
         "TO",
         [
            1,
            "fe"
         ],
         true
      ],
      [
         "TO",
         [
            1,
            "fe"
         ],
         true
      ],
      [
         "TO",
         [
            1,
            "fe"
         ],
         true
      ],
      [
         "TO",
         [
            1,
            "fe"
         ],
         true
      ],
      [
         "TO",
         [
            1,
            "fe"
         ],
         true
      ],
      [
         "TO",
         [
            1,
            "fe"
         ],
         true
      ],
      [
         "TO",
         [
            1,
            "fe"
         ],
         true
      ],
      [
         "TO",
         [
            1,
            "fe"
         ],
         true
      ],
      [
         "TO",
         [
            1,
            "fe"
         ],
         true
      ],
      [
         "TO",
         [
            1,
            "fe"
         ],
         true
      ],
      [
         "TO",
         [
            1,
            "fe"
         ],
         true
      ],
      [
         "TO",
         [
            1,
            "fe"
         ],
         true
      ],
      [
         "TO",
         [
            1,
            "fe"
         ],
         true
      ],
      [
         "TO",
         [
            1,
            "fe"
         ],
         true
      ],
      [
         "TO",
         [
            1,
            "fe"
         ],
         true
      ],
      [
         "TO",
         [
            1,
            "fe"
         ],
         true
      ],
      [
         "TO",
         [
            1,
            "fe"
         ],
         true
      ],
      [
         "TO",
         [
            1,
            "fe"
         ],
         true
      ],
      [
         "TO",
         [
            1,
            "fe"
         ],
         true
      ],
      [
         "TO",
         [
            1,
            "fe"
         ],
         true
      ],
      [
         "TO",
         [
            1,
            "fe"
         ],
         true
      ],
      [
         "TO",
         [
            1,
            "fe"
         ],
         true
      ],
      [
         "TO",
         [
            1,
            "fe"
         ],
         true
      ],
      [
         "TO",
         [
            1,
            "fe"
         ],
         true
      ],
      [
         "TO",
         [
            1,
            "fe"
         ],
         true
      ],
      [
         "TO",
         [
            1,
            "fe"
         ],
         true
      ],
      [
         "TO",
         [
            1,
            "fe"
         ],
         true
      ],
      [
         "TO",
         [
            1,
            "fe"
         ],
         true
      ],
      [
         "TO",
         [
            1,
            "fe"
         ],
         true
      ],
      [
         "TO",
         [
            1,
            "fe"
         ],
         true
      ],
      [
         "TO",
         [
            1,
            "fe"
         ],
         true
      ],
      [
         "TO",
         [
            1,
            "fe"
         ],
         true
      ],
      [
         "TO",
         [
            1,
            "fe"
         ],
         true
      ],
      [
         "TO",
         [
            1,
            "fe"
         ],
         true
      ],
      [
         "TO",
         [
            1,
            "fe"
         ],
         true
      ],
      [
         "TO",
         [
            1,
            "fe"
         ],
         true
      ],
      [
         "TO",
         [
            1,
            "fe"
         ],
         true
      ],
      [
         "TO",
         [
            1,
            "fe"
         ],
         true
      ],
      [
         "TO",
         [
            1,
            "fe"
         ],
         true
      ],
      [
         "TO",
         [
            1,
            "fe"
         ],
         true
      ],
      [
         "TO",
         [
            1,
            "fe"
         ],
         true
      ],
      [
         "TO",
         [
            1,
            "fe"
         ],
         true
      ],
      [
         "TO",
         [
            1,
            "fe"
         ],
         true
      ],
      [
         "TO",
         [
            1,
            "fe"
         ],
         true
      ],
      [
         "TO",
         [
            1,
            "fe"
         ],
         true
      ],
      [
         "TO",
         [
            1,
            "fe"
         ],
         true
      ],
      [
         "TO",
         [
            1,
            "fe"
         ],
         true
      ],
      [
         "TO",
         [
            1,
            "fe"
         ],
         true
      ],
      [
         "TO",
         [
            1,
            "fe"
         ],
         true
      ],
      [
         "TO",
         [
            1,
            "fe"
         ],
         true
      ],
      [
         "TO",
         [
            1,
            "fe"
         ],
         true
      ],
      [
         "TO",
         [
            1,
            "fe"
         ],
         true
      ],
      [
         "TO",
         [
            1,
            "fe"
         ],
         true
      ],
      [
         "TO",
         [
            1,
            "fe"
         ],
         true
      ],
      [
         "TO",
         [
            1,
            "fe"
         ],
         true
      ],
      [
         "TO",
         [
            1,
            "fe"
         ],
         true
      ],
      [
         "TO",
         [
            1,
            "fe"
         ],
         true
      ],
      [
         "TO",
         [
            1,
            "fe"
         ],
         true
      ],
      [
         "TO",
         [
            1,
            "fe"
         ],
         true
      ],
      [
         "TO",
         [
            1,
            "fe"
         ],
         true
      ],
      [
         "TO",
         [
            1,
            "fe"
         ],
         true
      ],
      [
         "TO",
         [
            1,
            "fe"
         ],
         true
      ],
      [
         "TO",
         [
            1,
            "fe"
         ],
         true
      ],
      [
         "TO",
         [
            1,
            "fe"
         ],
         true
      ],
      [
         "TO",
         [
            1,
            "fe"
         ],
         true
      ],
      [
         "TO",
         [
            1,
            "fe"
         ],
         true
      ],
      [
         "TO",
         [
            1,
            "fe"
         ],
         true
      ],
      [
         "TO",
         [
            1,
            "fe"
         ],
         true
      ],
      [
         "TO",
         [
            1,
            "fe"
         ],
         true
      ],
      [
         "TO",
         [
            1,
            "fe"
         ],
         true
      ],
      [
         "TO",
         [
            1,
            "fe"
         ],
         true
      ],
      [
         "TO",
         [
            1,
            "fe"
         ],
         true
      ],
      [
         "TO",
         [
            1,
            "fe"
         ],
         true
      ],
      [
         "TO",
         [
            1,
            "fe"
         ],
         true
      ],
      [
         "TO",
         [
            1,
            "fe"
         ],
         true
      ],
      [
         "TO",
         [
            1,
            "fe"
         ],
         true
      ],
      [
         "TO",
         [
            1,
            "fe"
         ],
         true
      ],
      [
         "TO",
         [
            1,
            "fe"
         ],
         true
      ],
      [
         "TO",
         [
            1,
            "fe"
         ],
         true
      ],
      [
         "TO",
         [
            1,
            "fe"
         ],
         true
      ],
      [
         "TO",
         [
            1,
            "fe"
         ],
         true
      ],
      [
         "TO",
         [
            1,
            "fe"
         ],
         true
      ],
      [
         "TO",
         [
            1,
            "fe"
         ],
         true
      ],
      [
         "TO",
         [
            1,
            "fe"
         ],
         true
      ],
      [
         "TO",
         [
            1,
            "fe"
         ],
         true
      ],
      [
         "TO",
         [
            1,
            "fe"
         ],
         true
      ],
      [
         "TO",
         [
            1,
            "fe"
         ],
         true
      ],
      [
         "TO",
         [
            1,
            "fe"
         ],
         true
      ],
      [
         "TO",
         [
            1,
            "fe"
         ],
         true
      ],
      [
         "TO",
         [
            1,
            "fe"
         ],
         true
      ],
      [
         "TO",
         [
            1,
            "fe"
         ],
         true
      ],
      [
         "TO",
         [
            1,
            "fe"
         ],
         true
      ],
      [
         "TO",
         [
            1,
            "fe"
         ],
         true
      ],
      [
         "TO",
         [
            1,
            "fe"
         ],
         true
      ],
      [
         "TO",
         [
            1,
            "fe"
         ],
         true
      ],
      [
         "TO",
         [
            1,
            "fe"
         ],
         true
      ],
      [
         "TO",
         [
            1,
            "fe"
         ],
         true
      ],
      [
         "TO",
         [
            1,
            "fe"
         ],
         true
      ],
      [
         "TO",
         [
            1,
            "fe"
         ],
         true
      ],
      [
         "TO",
         [
            1,
            "fe"
         ],
         true
      ],
      [
         "RO",
         [
            131,
            "8afd85cb6d3e7b3593c07b3593c07b3593c07b3593c07b3593c07b3593c07b3593c07b3593c07b3593c07b3593c07b3593c07b3593c07b3593c07b3593c07b35 ..."
         ]
      ],
      [
         "RF",
         [
            125,
            "0xfefefefefefefefefefefefefefefefefefefefefefefefefefefefefefefefefefefefefefefefefefefefefefefefefefefefefefefefefefefefefefefefe ..."
         ],
         10,
         true,
         0,
         true,
         "85cb6d3e"
      ],
      [
         "TF",
         [
            2,
            "0x03e8"
         ],
         8,
         true,
         0,
         null,
         null,
         null,
         false
      ],
      [
         "TO",
         [
            4,
            "880203e8"
         ],
         false
      ],
      [
         "RO",
         [
            8,
            "8882adab2117ae43"
         ]
      ],
      [
         "RF",
         [
            2,
            "0x03e8"
         ],
         8,
         true,
         0,
         true,
         "adab2117"
      ]
   ]
}