{
   "agent": "ws@8.17.0",
   "behavior": "OK",
   "behaviorClose": "OK",
   "case": 27,
   "closedByMe": true,
   "createStats": true,
   "createWirelog": true,
   "description": "Send 10 Pings with payload. Send out octets in octet-wise chops.",
   "droppedByMe": true,
   "duration": 25,
   "expectation": "Pongs for our Pings with all the payloads. Note: This is not required by the Spec .. but we check for this behaviour anyway. Clean close with normal code.",
   "expected": {
      "OK": [
         [
            "pong",
            "payload-0"
         ],
         [
            "pong",
            "payload-1"
         ],
         [
            "pong",
            "payload-2"
         ],
         [
            "pong",
            "payload-3"
         ],
         [
            "pong",
            "payload-4"
         ],
         [
            "pong",
            "payload-5"
         ],
         [
            "pong",
            "payload-6"
         ],
         [
            "pong",
            "payload-7"
         ],
         [
            "pong",
            "payload-8"
         ],
         [
            "pong",
            "payload-9"
         ]
      ]
   },
   "expectedClose": {
      "closeCode": [
         1000
      ],
      "closedByMe": true,
      "requireClean": true
   },
   "failedByMe": false,
   "httpRequest": "GET /runCase?case=27&agent=ws@8.17.0 HTTP/1.1\r\nSec-WebSocket-Version: 13\r\nSec-WebSocket-Key: QOyGjfmli0FoZ+o1QTC/tA==\r\nConnection: Upgrade\r\nUpgrade: websocket\r\nSec-WebSocket-Extensions: permessage-deflate; client_max_window_bits\r\nHost: localhost:9001\r\n\r\n",
   "httpResponse": "HTTP/1.1 101 Switching Protocols\r\nServer: AutobahnTestSuite/0.8.2-0.10.9\r\nX-Powered-By: AutobahnPython/0.10.9\r\nUpgrade: WebSocket\r\nConnection: Upgrade\r\nSec-WebSocket-Accept: AN4l+9KrTF2gGRSaxAdAIkPx1jI=\r\n\r\n",
   "id": "2.11",
   "isServer": true,
   "localCloseCode": 1000,
   "localCloseReason": null,
   "received": [
      [
         "pong",
         "payload-0"
      ],
      [
         "pong",
         "payload-1"
      ],
      [
         "pong",
         "payload-2"
      ],
      [
         "pong",
         "payload-3"
      ],
      [
         "pong",
         "payload-4"
      ],
      [
         "pong",
         "payload-5"
      ],
      [
         "pong",
         "payload-6"
      ],
      [
         "pong",
         "payload-7"
      ],
      [
         "pong",
         "payload-8"
      ],
      [
         "pong",
         "payload-9"
      ]
   ],
   "remoteCloseCode": 1000,
   "remoteCloseReason": null,
   "reportCompressionRatio": false,
   "reportTime": false,
   "result": "Actual events match at least one expected.",
   "resultClose": "Connection was properly closed",
   "rxFrameStats": {
      "8": 1,
      "10": 10
   },
   "rxOctetStats": {
      "8": 1,
      "15": 10,
      "254": 1
   },
   "started": "2024-05-17T17:42:49.090Z",
   "trafficStats": null,
   "txFrameStats": {
      "8": 1,
      "9": 10
   },
   "txOctetStats": {
      "1": 110,
      "4": 1,
      "206": 1
   },
   "wasClean": true,
   "wasCloseHandshakeTimeout": false,
   "wasNotCleanReason": null,
   "wasOpenHandshakeTimeout": false,
   "wasServerConnectionDropTimeout": false,
   "wirelog": [
      [
         "RO",
         [
            254,
            "474554202f72756e436173653f636173653d3237266167656e743d777340382e31372e3020485454502f312e310d0a5365632d576562536f636b65742d566572 ..."
         ]
      ],
      [
         "TO",
         [
            206,
            "485454502f312e312031303120537769746368696e672050726f746f636f6c730d0a5365727665723a204175746f6261686e5465737453756974652f302e382e ..."
         ],
         false
      ],
      [
         "TF",
         [
            9,
            "payload-0"
         ],
         9,
         true,
         0,
         null,
         null,
         1,
         false
      ],
      [
         "TO",
         [
            1,
            "89"
         ],
         true
      ],
      [
         "TF",
         [
            9,
            "payload-1"
         ],
         9,
         true,
         0,
         null,
         null,
         1,
         false
      ],
      [
         "TF",
         [
            9,
            "payload-2"
         ],
         9,
         true,
         0,
         null,
         null,
         1,
         false
      ],
      [
         "TF",
         [
            9,
            "payload-3"
         ],
         9,
         true,
         0,
         null,
         null,
         1,
         false
      ],
      [
         "TF",
         [
            9,
            "payload-4"
         ],
         9,
         true,
         0,
         null,
         null,
         1,
         false
      ],
      [
         "TF",
         [
            9,
            "payload-5"
         ],
         9,
         true,
         0,
         null,
         null,
         1,
         false
      ],
      [
         "TF",
         [
            9,
            "payload-6"
         ],
         9,
         true,
         0,
         null,
         null,
         1,
         false
      ],
      [
         "TF",
         [
            9,
            "payload-7"
         ],
         9,
         true,
         0,
         null,
         null,
         1,
         false
      ],
      [
         "TF",
         [
            9,
            "payload-8"
         ],
         9,
         true,
         0,
         null,
         null,
         1,
         false
      ],
      [
         "TF",
         [
            9,
            "payload-9"
         ],
         9,
         true,
         0,
         null,
         null,
         1,
         false
      ],
      [
         "TI",
         3
      ],
      [
         "TO",
         [
            1,
            "09"
         ],
         true
      ],
      [
         "TO",
         [
            1,
            "70"
         ],
         true
      ],
      [
         "TO",
         [
            1,
            "61"
         ],
         true
      ],
      [
         "TO",
         [
            1,
            "79"
         ],
         true
      ],
      [
         "TO",
         [
            1,
            "6c"
         ],
         true
      ],
      [
         "TO",
         [
            1,
            "6f"
         ],
         true
      ],
      [
         "TO",
         [
            1,
            "61"
         ],
         true
      ],
      [
         "TO",
         [
            1,
            "64"
         ],
         true
      ],
      [
         "TO",
         [
            1,
            "2d"
         ],
         true
      ],
      [
         "TO",
         [
            1,
            "30"
         ],
         true
      ],
      [
         "TO",
         [
            1,
            "89"
         ],
         true
      ],
      [
         "TO",
         [
            1,
            "09"
         ],
         true
      ],
      [
         "RO",
         [
            15,
            "8a896067ccd41006b5b80f06a8f950"
         ]
      ],
      [
         "RF",
         [
            9,
            "payload-0"
         ],
         10,
         true,
         0,
         true,
         "6067ccd4"
      ],
      [
         "TO",
         [
            1,
            "70"
         ],
         true
      ],
      [
         "TO",
         [
            1,
            "61"
         ],
         true
      ],
      [
         "TO",
         [
            1,
            "79"
         ],
         true
      ],
      [
         "TO",
         [
            1,
            "6c"
         ],
         true
      ],
      [
         "TO",
         [
            1,
            "6f"
         ],
         true
      ],
      [
         "TO",
         [
            1,
            "61"
         ],
         true
      ],
      [
         "TO",
         [
            1,
            "64"
         ],
         true
      ],
      [
         "TO",
         [
            1,
            "2d"
         ],
         true
      ],
      [
         "TO",
         [
            1,
            "31"
         ],
         true
      ],
      [
         "TO",
         [
            1,
            "89"
         ],
         true
      ],
      [
         "TO",
         [
            1,
            "09"
         ],
         true
      ],
      [
         "TO",
         [
            1,
            "70"
         ],
         true
      ],
      [
         "RO",
         [
            15,
            "8a89d211173ba2706e57bd707316e3"
         ]
      ],
      [
         "RF",
         [
            9,
            "payload-1"
         ],
         10,
         true,
         0,
         true,
         "d211173b"
      ],
      [
         "TO",
         [
            1,
            "61"
         ],
         true
      ],
      [
         "TO",
         [
            1,
            "79"
         ],
         true
      ],
      [
         "TO",
         [
            1,
            "6c"
         ],
         true
      ],
      [
         "TO",
         [
            1,
            "6f"
         ],
         true
      ],
      [
         "TO",
         [
            1,
            "61"
         ],
         true
      ],
      [
         "TO",
         [
            1,
            "64"
         ],
         true
      ],
      [
         "TO",
         [
            1,
            "2d"
         ],
         true
      ],
      [
         "TO",
         [
            1,
            "32"
         ],
         true
      ],
      [
         "TO",
         [
            1,
            "89"
         ],
         true
      ],
      [
         "TO",
         [
            1,
            "09"
         ],
         true
      ],
      [
         "RO",
         [
            15,
            "8a89168d2c9d66ec55f179ec48b024"
         ]
      ],
      [
         "RF",
         [
            9,
            "payload-2"
         ],
         10,
         true,
         0,
         true,
         "168d2c9d"
      ],
      [
         "TO",
         [
            1,
            "70"
         ],
         true
      ],
      [
         "TO",
         [
            1,
            "61"
         ],
         true
      ],
      [
         "TO",
         [
            1,
            "79"
         ],
         true
      ],
      [
         "TO",
         [
            1,
            "6c"
         ],
         true
      ],
      [
         "TO",
         [
            1,
            "6f"
         ],
         true
      ],
      [
         "TO",
         [
            1,
            "61"
         ],
         true
      ],
      [
         "TO",
         [
            1,
            "64"
         ],
         true
      ],
      [
         "TO",
         [
            1,
            "2d"
         ],
         true
      ],
      [
         "TO",
         [
            1,
            "33"
         ],
         true
      ],
      [
         "TO",
         [
            1,
            "89"
         ],
         true
      ],
      [
         "TO",
         [
            1,
            "09"
         ],
         true
      ],
      [
         "RO",
         [
            15,
            "8a89cf996a96bff813faa0f80ebbfc"
         ]
      ],
      [
         "RF",
         [
            9,
            "payload-3"
         ],
         10,
         true,
         0,
         true,
         "cf996a96"
      ],
      [
         "TO",
         [
            1,
            "70"
         ],
         true
      ],
      [
         "TO",
         [
            1,
            "61"
         ],
         true
      ],
      [
         "TO",
         [
            1,
            "79"
         ],
         true
      ],
      [
         "TO",
         [
            1,
            "6c"
         ],
         true
      ],
      [
         "TO",
         [
            1,
            "6f"
         ],
         true
      ],
      [
         "TO",
         [
            1,
            "61"
         ],
         true
      ],
      [
         "TO",
         [
            1,
            "64"
         ],
         true
      ],
      [
         "TO",
         [
            1,
            "2d"
         ],
         true
      ],
      [
         "TO",
         [
            1,
            "34"
         ],
         true
      ],
      [
         "TO",
         [
            1,
            "89"
         ],
         true
      ],
      [
         "TO",
         [
            1,
            "09"
         ],
         true
      ],
      [
         "TO",
         [
            1,
            "70"
         ],
         true
      ],
      [
         "RO",
         [
            15,
            "8a895797cae627f6b38a38f6aecb63"
         ]
      ],
      [
         "RF",
         [
            9,
            "payload-4"
         ],
         10,
         true,
         0,
         true,
         "5797cae6"
      ],
      [
         "TO",
         [
            1,
            "61"
         ],
         true
      ],
      [
         "TO",
         [
            1,
            "79"
         ],
         true
      ],
      [
         "TO",
         [
            1,
            "6c"
         ],
         true
      ],
      [
         "TO",
         [
            1,
            "6f"
         ],
         true
      ],
      [
         "TO",
         [
            1,
            "61"
         ],
         true
      ],
      [
         "TO",
         [
            1,
            "64"
         ],
         true
      ],
      [
         "TO",
         [
            1,
            "2d"
         ],
         true
      ],
      [
         "TO",
         [
            1,
            "35"
         ],
         true
      ],
      [
         "TO",
         [
            1,
            "89"
         ],
         true
      ],
      [
         "TO",
         [
            1,
            "09"
         ],
         true
      ],
      [
         "TO",
         [
            1,
            "70"
         ],
         true
      ],
      [
         "RO",
         [
            15,
            "8a8991a42fb5e1c556d9fec54b98a4"
         ]
      ],
      [
         "RF",
         [
            9,
            "payload-5"
         ],
         10,
         true,
         0,
         true,
         "91a42fb5"
      ],
      [
         "TO",
         [
            1,
            "61"
         ],
         true
      ],
      [
         "TO",
         [
            1,
            "79"
         ],
         true
      ],
      [
         "TO",
         [
            1,
            "6c"
         ],
         true
      ],
      [
         "TO",
         [
            1,
            "6f"
         ],
         true
      ],
      [
         "TO",
         [
            1,
            "61"
         ],
         true
      ],
      [
         "TO",
         [
            1,
            "64"
         ],
         true
      ],
      [
         "TO",
         [
            1,
            "2d"
         ],
         true
      ],
      [
         "TO",
         [
            1,
            "36"
         ],
         true
      ],
      [
         "TO",
         [
            1,
            "89"
         ],
         true
      ],
      [
         "TO",
         [
            1,
            "09"
         ],
         true
      ],
      [
         "TO",
         [
            1,
            "70"
         ],
         true
      ],
      [
         "RO",
         [
            15,
            "8a891ec4693b6ea5105771a50d1628"
         ]
      ],
      [
         "RF",
         [
            9,
            "payload-6"
         ],
         10,
         true,
         0,
         true,
         "1ec4693b"
      ],
      [
         "TO",
         [
            1,
            "61"
         ],
         true
      ],
      [
         "TO",
         [
            1,
            "79"
         ],
         true
      ],
      [
         "TO",
         [
            1,
            "6c"
         ],
         true
      ],
      [
         "TO",
         [
            1,
            "6f"
         ],
         true
      ],
      [
         "TO",
         [
            1,
            "61"
         ],
         true
      ],
      [
         "TO",
         [
            1,
            "64"
         ],
         true
      ],
      [
         "TO",
         [
            1,
            "2d"
         ],
         true
      ],
      [
         "TO",
         [
            1,
            "37"
         ],
         true
      ],
      [
         "TO",
         [
            1,
            "89"
         ],
         true
      ],
      [
         "TO",
         [
            1,
            "09"
         ],
         true
      ],
      [
         "TO",
         [
            1,
            "70"
         ],
         true
      ],
      [
         "RO",
         [
            15,
            "8a896220347412414d180d41505955"
         ]
      ],
      [
         "RF",
         [
            9,
            "payload-7"
         ],
         10,
         true,
         0,
         true,
         "62203474"
      ],
      [
         "TO",
         [
            1,
            "61"
         ],
         true
      ],
      [
         "TO",
         [
            1,
            "79"
         ],
         true
      ],
      [
         "TO",
         [
            1,
            "6c"
         ],
         true
      ],
      [
         "TO",
         [
            1,
            "6f"
         ],
         true
      ],
      [
         "TO",
         [
            1,
            "61"
         ],
         true
      ],
      [
         "TO",
         [
            1,
            "64"
         ],
         true
      ],
      [
         "TO",
         [
            1,
            "2d"
         ],
         true
      ],
      [
         "TO",
         [
            1,
            "38"
         ],
         true
      ],
      [
         "TO",
         [
            1,
            "89"
         ],
         true
      ],
      [
         "TO",
         [
            1,
            "09"
         ],
         true
      ],
      [
         "TO",
         [
            1,
            "70"
         ],
         true
      ],
      [
         "RO",
         [
            15,
            "8a89c5094d3db5683451aa682910fd"
         ]
      ],
      [
         "RF",
         [
            9,
            "payload-8"
         ],
         10,
         true,
         0,
         true,
         "c5094d3d"
      ],
      [
         "TO",
         [
            1,
            "61"
         ],
         true
      ],
      [
         "TO",
         [
            1,
            "79"
         ],
         true
      ],
      [
         "TO",
         [
            1,
            "6c"
         ],
         true
      ],
      [
         "TO",
         [
            1,
            "6f"
         ],
         true
      ],
      [
         "TO",
         [
            1,
            "61"
         ],
         true
      ],
      [
         "TO",
         [
            1,
            "64"
         ],
         true
      ],
      [
         "TO",
         [
            1,
            "2d"
         ],
         true
      ],
      [
         "TO",
         [
            1,
            "39"
         ],
         true
      ],
      [
         "RO",
         [
            15,
            "8a899d7fe86eed1e9102f21e8c43a4"
         ]
      ],
      [
         "RF",
         [
            9,
            "payload-9"
         ],
         10,
         true,
         0,
         true,
         "9d7fe86e"
      ],
      [
         "TF",
         [
            2,
            "0x03e8"
         ],
         8,
         true,
         0,
         null,
         null,
         null,
         false
      ],
      [
         "TO",
         [
            4,
            "880203e8"
         ],
         false
      ],
      [
         "RO",
         [
            8,
            "88823f39d1ec3cd1"
         ]
      ],
      [
         "RF",
         [
            2,
            "0x03e8"
         ],
         8,
         true,
         0,
         true,
         "3f39d1ec"
      ]
   ]
}