{
   "agent": "ws@8.17.0",
   "behavior": "OK",
   "behaviorClose": "OK",
   "case": 303,
   "closedByMe": true,
   "createStats": true,
   "createWirelog": true,
   "description": "Send 1000 compressed messages each of payload size 64, auto-fragment to 0 octets. Use default permessage-deflate offer.",
   "droppedByMe": false,
   "duration": 761,
   "expectation": "Receive echo'ed messages (with payload as sent). Timeout case after 60 secs.",
   "expected": {},
   "expectedClose": {
      "closeCode": [
         1000
      ],
      "closedByMe": true,
      "requireClean": true
   },
   "failedByMe": false,
   "httpRequest": "GET / HTTP/1.1\r\nUser-Agent: AutobahnTestSuite/0.8.2-0.10.9\r\nHost: 192.168.0.103:9002\r\nUpgrade: WebSocket\r\nConnection: Upgrade\r\nPragma: no-cache\r\nCache-Control: no-cache\r\nSec-WebSocket-Key: +DjJRakC6imkrSi0JIxM9w==\r\nSec-WebSocket-Extensions: permessage-deflate; client_no_context_takeover; client_max_window_bits\r\nSec-WebSocket-Version: 13\r\n\r\n",
   "httpResponse": "HTTP/1.1 101 Switching Protocols\r\nUpgrade: websocket\r\nConnection: Upgrade\r\nSec-WebSocket-Accept: 7fbTp0ONHFRuJleqnF7QBlRWaPU=\r\nSec-WebSocket-Extensions: permessage-deflate; client_no_context_takeover\r\n\r\n",
   "id": "12.1.2",
   "isServer": false,
   "localCloseCode": 1000,
   "localCloseReason": null,
   "received": [],
   "remoteCloseCode": 1000,
   "remoteCloseReason": null,
   "reportCompressionRatio": true,
   "reportTime": true,
   "result": "Ok, received all echo'ed messages in time.",
   "resultClose": "Connection was properly closed",
   "rxFrameStats": {
      "1": 1000,
      "8": 1
   },
   "rxOctetStats": {
      "4": 1,
      "7": 441,
      "8": 10,
      "9": 143,
      "10": 174,
      "11": 36,
      "12": 68,
      "13": 78,
      "14": 28,
      "15": 16,
      "19": 1,
      "24": 1,
      "32": 1,
      "37": 1,
      "38": 1,
      "51": 1,
      "203": 1
   },
   "started": "2024-05-17T18:00:33.660Z",
   "trafficStats": {
      "incomingCompressionRatio": 0.113328125,
      "incomingOctetsAppLevel": 64000,
      "incomingOctetsWebSocketLevel": 7253,
      "incomingOctetsWireLevel": 9253,
      "incomingWebSocketFrames": 1000,
      "incomingWebSocketMessages": 1000,
      "incomingWebSocketOverhead": 0.2757479663587481,
      "outgoingCompressionRatio": 0.7481875,
      "outgoingOctetsAppLevel": 64000,
      "outgoingOctetsWebSocketLevel": 47884,
      "outgoingOctetsWireLevel": 53884,
      "outgoingWebSocketFrames": 1000,
      "outgoingWebSocketMessages": 1000,
      "outgoingWebSocketOverhead": 0.12530281513658006,
      "preopenIncomingOctetsWireLevel": 203,
      "preopenOutgoingOctetsWireLevel": 342
   },
   "txFrameStats": {
      "1": 1000,
      "8": 1
   },
   "txOctetStats": {
      "8": 1,
      "39": 5,
      "40": 8,
      "41": 31,
      "42": 35,
      "43": 11,
      "44": 15,
      "45": 17,
      "46": 20,
      "47": 22,
      "48": 56,
      "49": 54,
      "50": 16,
      "51": 50,
      "52": 76,
      "53": 83,
      "54": 84,
      "55": 61,
      "56": 40,
      "57": 21,
      "58": 11,
      "59": 16,
      "60": 11,
      "61": 30,
      "62": 89,
      "63": 68,
      "64": 36,
      "65": 14,
      "66": 15,
      "67": 5,
      "342": 1
   },
   "wasClean": true,
   "wasCloseHandshakeTimeout": false,
   "wasNotCleanReason": null,
   "wasOpenHandshakeTimeout": false,
   "wasServerConnectionDropTimeout": false,
   "wirelog": [
      [
         "TO",
         [
            342,
            "474554202f20485454502f312e310d0a557365722d4167656e743a204175746f6261686e5465737453756974652f302e382e322d302e31302e390d0a486f7374 ..."
         ],
         false
      ],
      [
         "RO",
         [
            203,
            "485454502f312e312031303120537769746368696e672050726f746f636f6c730d0a557067726164653a20776562736f636b65740d0a436f6e6e656374696f6e ..."
         ]
      ],
      [
         "WLM",
         false
      ],
      [
         "TI",
         60
      ],
      [
         "WLM",
         true
      ],
      [
         "TF",
         [
            2,
            "0x03e8"
         ],
         8,
         true,
         0,
         "d0eea207",
         null,
         null,
         false
      ],
      [
         "TO",
         [
            8,
            "8882d0eea207d306"
         ],
         false
      ],
      [
         "RO",
         [
            4,
            "880203e8"
         ]
      ],
      [
         "RF",
         [
            2,
            "0x03e8"
         ],
         8,
         true,
         0,
         false,
         null
      ]
   ]
}