{
   "agent": "ws@8.17.0",
   "behavior": "OK",
   "behaviorClose": "OK",
   "case": 63,
   "closedByMe": true,
   "createStats": true,
   "createWirelog": true,
   "description": "A fragmented text message is sent in multiple frames. After\n   sending the first 2 frames of the text message, a Ping is sent. Then we wait 1s,\n   then we send 2 more text fragments, another Ping and then the final text fragment.\n   Everything is legal.",
   "droppedByMe": false,
   "duration": 1004,
   "expectation": "The peer immediately answers the first Ping before\n   it has received the last text message fragment. The peer pong's back the Ping's\n   payload exactly, and echo's the payload of the fragmented message back to us.",
   "expected": {
      "OK": [
         [
            "pong",
            "pongme 1!"
         ],
         [
            "pong",
            "pongme 2!"
         ],
         [
            "message",
            "fragment1fragment2fragment3fragment4fragment5",
            false
         ]
      ]
   },
   "expectedClose": {
      "closeCode": [
         1000
      ],
      "closedByMe": true,
      "requireClean": true
   },
   "failedByMe": false,
   "httpRequest": "GET / HTTP/1.1\r\nUser-Agent: AutobahnTestSuite/0.8.2-0.10.9\r\nHost: 192.168.0.103:9002\r\nUpgrade: WebSocket\r\nConnection: Upgrade\r\nPragma: no-cache\r\nCache-Control: no-cache\r\nSec-WebSocket-Key: YB6YOkYghZ5ebeUb8cqWGg==\r\nSec-WebSocket-Version: 13\r\n\r\n",
   "httpResponse": "HTTP/1.1 101 Switching Protocols\r\nUpgrade: websocket\r\nConnection: Upgrade\r\nSec-WebSocket-Accept: +v23EY91fJS6H5f5hPYr9wOaysQ=\r\n\r\n",
   "id": "5.19",
   "isServer": false,
   "localCloseCode": 1000,
   "localCloseReason": null,
   "received": [
      [
         "pong",
         "pongme 1!"
      ],
      [
         "pong",
         "pongme 2!"
      ],
      [
         "message",
         "fragment1fragment2fragment3fragment4fragment5",
         false
      ]
   ],
   "remoteCloseCode": 1000,
   "remoteCloseReason": null,
   "reportCompressionRatio": false,
   "reportTime": false,
   "result": "Actual events match at least one expected.",
   "resultClose": "Connection was properly closed",
   "rxFrameStats": {
      "1": 1,
      "8": 1,
      "10": 2
   },
   "rxOctetStats": {
      "4": 1,
      "11": 1,
      "58": 1,
      "129": 1
   },
   "started": "2024-05-17T18:00:12.647Z",
   "trafficStats": null,
   "txFrameStats": {
      "0": 4,
      "1": 1,
      "8": 1,
      "9": 2
   },
   "txOctetStats": {
      "8": 1,
      "15": 7,
      "244": 1
   },
   "wasClean": true,
   "wasCloseHandshakeTimeout": false,
   "wasNotCleanReason": null,
   "wasOpenHandshakeTimeout": false,
   "wasServerConnectionDropTimeout": false,
   "wirelog": [
      [
         "TO",
         [
            244,
            "474554202f20485454502f312e310d0a557365722d4167656e743a204175746f6261686e5465737453756974652f302e382e322d302e31302e390d0a486f7374 ..."
         ],
         false
      ],
      [
         "RO",
         [
            129,
            "485454502f312e312031303120537769746368696e672050726f746f636f6c730d0a557067726164653a20776562736f636b65740d0a436f6e6e656374696f6e ..."
         ]
      ],
      [
         "TF",
         [
            9,
            "fragment1"
         ],
         1,
         false,
         0,
         "6b6ea6ac",
         null,
         null,
         false
      ],
      [
         "TO",
         [
            15,
            "01896b6ea6ac0d1cc7cb060bc8d85a"
         ],
         false
      ],
      [
         "TF",
         [
            9,
            "fragment2"
         ],
         0,
         false,
         0,
         "8f62c591",
         null,
         null,
         false
      ],
      [
         "TO",
         [
            15,
            "00898f62c591e910a4f6e207abe5bd"
         ],
         false
      ],
      [
         "TF",
         [
            9,
            "pongme 1!"
         ],
         9,
         true,
         0,
         "3169b355",
         null,
         null,
         false
      ],
      [
         "TO",
         [
            15,
            "89893169b3554106dd325c0c936410"
         ],
         false
      ],
      [
         "CT",
         1,
         null
      ],
      [
         "RO",
         [
            11,
            "8a09706f6e676d65203121"
         ]
      ],
      [
         "RF",
         [
            9,
            "pongme 1!"
         ],
         10,
         true,
         0,
         false,
         null
      ],
      [
         "CTE",
         null
      ],
      [
         "TF",
         [
            9,
            "fragment3"
         ],
         0,
         false,
         0,
         "aa6d831b",
         null,
         null,
         false
      ],
      [
         "TO",
         [
            15,
            "0089aa6d831bcc1fe27cc708ed6f99"
         ],
         false
      ],
      [
         "TF",
         [
            9,
            "fragment4"
         ],
         0,
         false,
         0,
         "38996c2e",
         null,
         null,
         false
      ],
      [
         "TO",
         [
            15,
            "008938996c2e5eeb0d4955fc025a0c"
         ],
         false
      ],
      [
         "TF",
         [
            9,
            "pongme 2!"
         ],
         9,
         true,
         0,
         "9225c6db",
         null,
         null,
         false
      ],
      [
         "TO",
         [
            15,
            "89899225c6dbe24aa8bcff40e6e9b3"
         ],
         false
      ],
      [
         "TF",
         [
            9,
            "fragment5"
         ],
         0,
         true,
         0,
         "4fd7b1b7",
         null,
         null,
         false
      ],
      [
         "TO",
         [
            15,
            "80894fd7b1b729a5d0d022b2dfc37a"
         ],
         false
      ],
      [
         "TI",
         1
      ],
      [
         "RO",
         [
            58,
            "8a09706f6e676d65203221812d667261676d656e7431667261676d656e7432667261676d656e7433667261676d656e7434667261676d656e7435"
         ]
      ],
      [
         "RF",
         [
            9,
            "pongme 2!"
         ],
         10,
         true,
         0,
         false,
         null
      ],
      [
         "RF",
         [
            45,
            "fragment1fragment2fragment3fragment4fragment5"
         ],
         1,
         true,
         0,
         false,
         null
      ],
      [
         "TF",
         [
            2,
            "0x03e8"
         ],
         8,
         true,
         0,
         "298d95a0",
         null,
         null,
         false
      ],
      [
         "TO",
         [
            8,
            "8882298d95a02a65"
         ],
         false
      ],
      [
         "RO",
         [
            4,
            "880203e8"
         ]
      ],
      [
         "RF",
         [
            2,
            "0x03e8"
         ],
         8,
         true,
         0,
         false,
         null
      ]
   ]
}